pypartial/__init__.py
pypartial-1.0.3.dist-info/DESCRIPTION.rst
pypartial-1.0.3.dist-info/METADATA
pypartial-1.0.3.dist-info/RECORD
pypartial-1.0.3.dist-info/WHEEL
pypartial-1.0.3.dist-info/metadata.json
pypartial-1.0.3.dist-info/top_level.txt
