Metadata-Version: 2.0
Name: pypartial
Version: 1.0.3
Summary: Use partial function application in Python
Home-page: https://pypi.python.org/pypi/pypartial
Author: Akif Patel
Author-email: akifpatel@supernovaapps.com
License: Apache 2.0
Keywords: python,functional programming,library,notation
Platform: UNKNOWN
Classifier: Development Status :: 4 - Beta
Classifier: Intended Audience :: Developers
Classifier: License :: OSI Approved :: Apache Software License
Classifier: Programming Language :: Python :: 3
Classifier: Topic :: Software Development :: Libraries :: Python Modules
